{
  "custom-stuff": {
    "category": "ambient",
    "sounds": [
      {
        "name": "custom/allaboutthatbass",
        "stream": true
      },
      {
        "name": "custom/anotherone",
        "stream": true
      },
      {
        "name": "custom/badblood",
        "stream": true
      },
      {
        "name": "custom/barney1",
        "stream": true
      },
      {
        "name": "custom/barney2",
        "stream": true
      },
      {
        "name": "custom/boomboomboom",
        "stream": true
      },
      {
        "name": "custom/boomslam",
        "stream": true
      },
      {
        "name": "custom/buildasnowman",
        "stream": true
      },
      {
        "name": "custom/cantbreath",
        "stream": true
      },
      {
        "name": "custom/christmas.rudolph",
        "stream": true
      },
      {
        "name": "custom/christmas.sleighbells",
        "stream": true
      },
      {
        "name": "custom/christmas.songs",
        "stream": true
      },
      {
        "name": "custom/christmas.white",
        "stream": true
      },
      {
        "name": "custom/coconut",
        "stream": true
      },
      {
        "name": "custom/comingtotakemeaway",
        "stream": true
      },
      {
        "name": "custom/cookieman",
        "stream": true
      },
      {
        "name": "custom/crazyfrog",
        "stream": true
      },
      {
        "name": "custom/darude",
        "stream": true
      },
      {
        "name": "custom/dramatic",
        "stream": true
      },
      {
        "name": "custom/drivinghard1",
        "stream": true
      },
      {
        "name": "custom/drivinghard2",
        "stream": true
      },
      {
        "name": "custom/fallenandcantgetup",
        "stream": true
      },
      {
        "name": "custom/gangnam1",
        "stream": true
      },
      {
        "name": "custom/gangnam2",
        "stream": true
      },
      {
        "name": "custom/getuprightnow",
        "stream": true
      },
      {
        "name": "custom/goodforyou",
        "stream": true
      },
      {
        "name": "custom/happy",
        "stream": true
      },
      {
        "name": "custom/happybday",
        "stream": true
      },
      {
        "name": "custom/inmemumscar",
        "stream": true
      },
      {
        "name": "custom/internet",
        "stream": true
      },
      {
        "name": "custom/iwroteasong",
        "stream": true
      },
      {
        "name": "custom/johncena.hello",
        "stream": true
      },
      {
        "name": "custom/johncena.music",
        "stream": true
      },
      {
        "name": "custom/johncena.mynameis",
        "stream": true
      },
      {
        "name": "custom/johncena.sith",
        "stream": true
      },
      {
        "name": "custom/johncena.trumpets",
        "stream": true
      },
      {
        "name": "custom/justdoit1",
        "stream": true
      },
      {
        "name": "custom/justdoit2",
        "stream": true
      },
      {
        "name": "custom/justdoit3",
        "stream": true
      },
      {
        "name": "custom/mlgmarriage",
        "stream": true
      },
      {
        "name": "custom/music1",
        "stream": true
      },
      {
        "name": "custom/music2",
        "stream": true
      },
      {
        "name": "custom/music3",
        "stream": true
      },
      {
        "name": "custom/music4",
        "stream": true
      },
      {
        "name": "custom/music5",
        "stream": true
      },
      {
        "name": "custom/music6",
        "stream": true
      },
      {
        "name": "custom/music7",
        "stream": true
      },
      {
        "name": "custom/music8",
        "stream": true
      },
      {
        "name": "custom/music9",
        "stream": true
      },
      {
        "name": "custom/music10",
        "stream": true
      },
      {
        "name": "custom/music11",
        "stream": true
      },
      {
        "name": "custom/music12",
        "stream": true
      },
      {
        "name": "custom/mylittlepony",
        "stream": true
      },
      {
        "name": "custom/nothisisscrub",
        "stream": true
      },
      {
        "name": "custom/pingu",
        "stream": true
      },
      {
        "name": "custom/reallyreallyreally",
        "stream": true
      },
      {
        "name": "custom/rickroll",
        "stream": true
      },
      {
        "name": "custom/soldierboy",
        "stream": true
      },
      {
        "name": "custom/soldierboy.dubstep",
        "stream": true
      },
      {
        "name": "custom/soldierboy.techno",
        "stream": true
      },
      {
        "name": "custom/sonisstarving",
        "stream": true
      },
      {
        "name": "custom/sonsfavourite",
        "stream": true
      },
      {
        "name": "custom/spacebomb",
        "stream": true
      },
      {
        "name": "custom/spookyscaryskeles",
        "stream": true
      },
      {
        "name": "custom/starwars",
        "stream": true
      },
      {
        "name": "custom/story",
        "stream": true
      },
      {
        "name": "custom/strawberryshortcake",
        "stream": true
      },
      {
        "name": "custom/subway",
        "stream": true
      },
      {
        "name": "custom/supercala",
        "stream": true
      },
      {
        "name": "custom/tf2.heavymusic",
        "stream": true
      },
      {
        "name": "custom/thegame",
        "stream": true
      },
      {
        "name": "custom/thingsflyaround",
        "stream": true
      },
      {
        "name": "custom/trumpets",
        "stream": true
      },
      {
        "name": "custom/tsunami",
        "stream": true
      },
      {
        "name": "custom/turndownforwhat",
        "stream": true
      },
      {
        "name": "custom/unknown1",
        "stream": true
      },
      {
        "name": "custom/unknown2",
        "stream": true
      },
      {
        "name": "custom/unknown3",
        "stream": true
      },
      {
        "name": "custom/welcometothejungle",
        "stream": true
      }
    ]
}
}